setup.py
bcc/__init__.py
bcc/containers.py
bcc/disassembler.py
bcc/libbcc.py
bcc/perf.py
bcc/syscall.py
bcc/table.py
bcc/tcp.py
bcc/usdt.py
bcc/utils.py
bcc/version.py
bcc_python.egg-info/PKG-INFO
bcc_python.egg-info/SOURCES.txt
bcc_python.egg-info/dependency_links.txt
bcc_python.egg-info/top_level.txt
bin/argdist
bin/bashreadline
bin/bindsnoop
bin/biolatency
bin/biolatpcts
bin/biopattern
bin/biosnoop
bin/biotop
bin/bitesize
bin/bpflist
bin/btrfsdist
bin/btrfsslower
bin/cachestat
bin/cachetop
bin/capable
bin/compactsnoop
bin/cpudist
bin/cpuunclaimed
bin/criticalstat
bin/dbslower
bin/dbstat
bin/dcsnoop
bin/dcstat
bin/deadlock
bin/dirtop
bin/drsnoop
bin/execsnoop
bin/exitsnoop
bin/ext4dist
bin/ext4slower
bin/filelife
bin/fileslower
bin/filetop
bin/funccount
bin/funcinterval
bin/funclatency
bin/funcslower
bin/gethostlatency
bin/hardirqs
bin/inject
bin/killsnoop
bin/klockstat
bin/kvmexit
bin/llcstat
bin/mdflush
bin/memleak
bin/mountsnoop
bin/mysqld_qslower
bin/netqtop
bin/nfsdist
bin/nfsslower
bin/offcputime
bin/offwaketime
bin/oomkill
bin/opensnoop
bin/pidpersec
bin/profile
bin/readahead
bin/runqlat
bin/runqlen
bin/runqslower
bin/shmsnoop
bin/slabratetop
bin/sofdsnoop
bin/softirqs
bin/solisten
bin/sslsniff
bin/stackcount
bin/statsnoop
bin/swapin
bin/syncsnoop
bin/syscount
bin/tcpaccept
bin/tcpcong
bin/tcpconnect
bin/tcpconnlat
bin/tcpdrop
bin/tcplife
bin/tcpretrans
bin/tcprtt
bin/tcpstates
bin/tcpsubnet
bin/tcpsynbl
bin/tcptop
bin/tcptracer
bin/threadsnoop
bin/tplist
bin/trace
bin/ttysnoop
bin/vfscount
bin/vfsstat
bin/virtiostat
bin/wakeuptime
bin/xfsdist
bin/xfsslower
bin/zfsdist