Metadata-Version: 1.2
Name: bcc-python
Version: 0.0.2
Summary: bcc-python
Home-page: https://github.com/Neeky/bcc-python
Author: Neeky
Author-email: neeky@live.com
Maintainer: Neeky
Maintainer-email: neeky@live.com
License: UNKNOWN
Platform: UNKNOWN
Classifier: Development Status :: 4 - Beta
Classifier: Intended Audience :: Developers
Classifier: Operating System :: POSIX
Classifier: Programming Language :: Python :: 3.6
Classifier: Programming Language :: Python :: 3.7
Classifier: Programming Language :: Python :: 3.8
Classifier: Programming Language :: Python :: 3.9
Classifier: Programming Language :: Python :: 3.10
Classifier: Programming Language :: Python :: 3.11
Requires-Python: >=3.6.*
